var_mesh/__init__.py
var_mesh/gen_mesh.py
var_mesh/helpers.py
var_mesh-1.0.2.dist-info/LICENSE
var_mesh-1.0.2.dist-info/METADATA
var_mesh-1.0.2.dist-info/WHEEL
var_mesh-1.0.2.dist-info/top_level.txt
var_mesh-1.0.2.dist-info/RECORD
