Metadata-Version: 2.1
Name: var-mesh
Version: 1.0.2
Summary: Variational Mesh
Home-page: https://gitlab.com/wangenau/variational_mesh
Author: Wanja Schulze
Author-email: wangenau@protonmail.com
License: APACHE2.0
Platform: UNKNOWN
Requires-Python: >=2.7 ,>=3.4
Requires-Dist: matplotlib
Requires-Dist: numpy
Requires-Dist: pyscf (>=1.7)
